nbi_stat/__init__.py
nbi_stat-0.8.5.dist-info/LICENSE
nbi_stat-0.8.5.dist-info/METADATA
nbi_stat-0.8.5.dist-info/WHEEL
nbi_stat-0.8.5.dist-info/top_level.txt
nbi_stat-0.8.5.dist-info/RECORD
