Metadata-Version: 2.1
Name: nbi-stat
Version: 0.8.5
Summary: Statistics tools for teaching at NBI
Home-page: https://cholmcc.gitlab.io/nbi-python/statistics/#Statistik
Author: Christian Holm Christensen
Author-email: cholmcc@gmail.com
License: GPL
Project-URL: Documentation, https://cholmcc.gitlab.io/nbi-python/statistics/nbi_stat
Project-URL: Source Code, https://gitlab.com/cholmcc/nbi-python
Keywords: Niels Bohr Institute,Physics,Statistics,Fitting,Rounding,Histogram,Random distribution,Visualizing,Tabulating
Classifier: License :: OSI Approved :: GNU General Public License v3 (GPLv3)
Classifier: Programming Language :: Python :: 3
Classifier: Intended Audience :: Education
Classifier: Intended Audience :: Science/Research
Classifier: Topic :: Scientific/Engineering :: Physics
Requires-Python: >=3.6
License-File: LICENSE
Requires-Dist: numpy >=1.16
Requires-Dist: scipy >=1.3
Requires-Dist: matplotlib >=3.0
